.DS_Store
api/__init__.py
api/face_network.py
face_network-1.0.2.dist-info/LICENSE
face_network-1.0.2.dist-info/METADATA
face_network-1.0.2.dist-info/WHEEL
face_network-1.0.2.dist-info/top_level.txt
face_network-1.0.2.dist-info/RECORD
