Metadata-Version: 2.1
Name: face-network
Version: 1.0.2
Summary: Create a social network graph based on coappearance in images
Home-page: https://github.com/oballinger/face-network
Author: Ollie Ballinger
Author-email: ollie.l.ballinger@gmail.com
License: MIT
Keywords: python,image,network,AI,neural network
Platform: UNKNOWN
Classifier: License :: OSI Approved :: MIT License
Classifier: Programming Language :: Python :: 3
Classifier: Programming Language :: Python :: 3.7
